{
    "name": "Dũng Nhữ Hoàng",
    "linkedin_url": "https://www.linkedin.com/in/d%C5%A9ng-nh%E1%BB%AF-ho%C3%A0ng-639139131",
    "about": [
        "i'm leader recuiter & headhunt of Ocean Edu for 01/08/2016"
    ],
    "experiences": [
        {
            "institution_name": "Ocean Edu",
            "website": "https://www.linkedin.com/company/6822487/",
            "industry": null,
            "type": null,
            "headquarters": null,
            "company_size": null,
            "founded": null,
            "from_date": "Jan 2007",
            "to_date": "Present",
            "description": null,
            "position_title": "Human Resources",
            "duration": "16 yrs",
            "location": null,
            "times": null
        }
    ],
    "educations": [
        {
            "institution_name": "National Economics University (Vietnam)",
            "website": "https://www.linkedin.com/company/13315365/",
            "industry": null,
            "type": null,
            "headquarters": null,
            "company_size": null,
            "founded": null,
            "from_date": "2010",
            "to_date": "2014",
            "description": null,
            "degree": "above average",
            "field_of_study": "FACULTY OF HUMAN RESOURCES ECONOMICS AND MANAGEMENT",
            "grade": null,
            "activities": null
        }
    ],
    "interests": [],
    "accomplishments": [],
    "also_viewed_urls": [],
    "contacts": [],
    "skills": [
        {
            "name": "Customer Service",
            "tag": "INDUSTRY-KNOWLEDGE"
        },
        {
            "name": "Training",
            "tag": "INDUSTRY-KNOWLEDGE"
        },
        {
            "name": "Teamwork",
            "tag": "INTERPERSONAL-SKILLS"
        },
        {
            "name": "Leadership",
            "tag": "INTERPERSONAL-SKILLS"
        },
        {
            "name": "Team Leadership",
            "tag": "INTERPERSONAL-SKILLS"
        },
        {
            "name": "Management",
            "tag": "INTERPERSONAL-SKILLS"
        }
    ]
}